plasticorigins/__init__.py
plasticorigins/detection/__init__.py
plasticorigins/detection/centernet/__init__.py
plasticorigins/detection/centernet/models.py
plasticorigins/detection/centernet/networks/__init__.py
plasticorigins/detection/centernet/networks/mobilenet.py
plasticorigins/detection/coco_utils.py
plasticorigins/detection/detect.py
plasticorigins/detection/losses.py
plasticorigins/detection/transforms.py
plasticorigins/detection/yolo.py
plasticorigins/serving/__init__.py
plasticorigins/serving/app.py
plasticorigins/serving/config.py
plasticorigins/serving/inference.py
plasticorigins/serving/templates/results.html
plasticorigins/serving/templates/upload.html
plasticorigins/serving/wsgi.py
plasticorigins/tools/__init__.py
plasticorigins/tools/files.py
plasticorigins/tools/misc.py
plasticorigins/tools/optical_flow.py
plasticorigins/tools/video_readers.py
plasticorigins/tracking/__init__.py
plasticorigins/tracking/postprocess_and_count_tracks.py
plasticorigins/tracking/track_video.py
plasticorigins/tracking/trackers.py
plasticorigins/tracking/utils.py
plasticorigins/training/LICENSE
plasticorigins/training/Makefile
plasticorigins/training/__init__.py
plasticorigins/training/azure/azure_ml.py
plasticorigins/training/data/.gitkeep
plasticorigins/training/data/__init__.py
plasticorigins/training/data/data_processing.py
plasticorigins/training/data/make_dataset.py
plasticorigins/training/data/make_dataset2.py
plasticorigins/training/docs/Makefile
plasticorigins/training/docs/commands.rst
plasticorigins/training/docs/conf.py
plasticorigins/training/docs/getting-started.rst
plasticorigins/training/docs/index.rst
plasticorigins/training/docs/make.bat
plasticorigins/training/setup.py
plasticorigins/training/test_environment.py
plasticorigins/training/visualization/.gitkeep
plasticorigins/training/visualization/__init__.py
plasticorigins/training/visualization/categories.py
plastic_origins-2.2.4.dist-info/METADATA
plastic_origins-2.2.4.dist-info/WHEEL
plastic_origins-2.2.4.dist-info/RECORD
