Metadata-Version: 2.1
Name: plastic-origins
Version: 2.2.4
Summary: A package containing methods commonly used to make inferences
Home-page: https://www.plasticorigins.eu/
License: MIT
Author: Chayma Mesbahi
Author-email: chayma.mesbahi@neoxia.com
Requires-Python: >=3.8,<3.11
Classifier: License :: OSI Approved :: MIT License
Classifier: Programming Language :: Python :: 3
Classifier: Programming Language :: Python :: 3.8
Classifier: Programming Language :: Python :: 3.9
Classifier: Programming Language :: Python :: 3.10
Requires-Dist: Flask (==2.0.3)
Requires-Dist: Pillow (==9.1.1)
Requires-Dist: Werkzeug (==2.0.3)
Requires-Dist: azure-identity (>=1.12.0,<2.0.0)
Requires-Dist: azure-keyvault-secrets (>=4.6.0,<5.0.0)
Requires-Dist: azure-storage-blob (>=12.14.1,<13.0.0)
Requires-Dist: debugpy (==1.5.1)
Requires-Dist: gunicorn (>=20.1.0,<21.0.0)
Requires-Dist: imgaug (==0.4.0)
Requires-Dist: mkdocs (>=1.4.2,<2.0.0)
Requires-Dist: opencv-python (==4.5.5.62)
Requires-Dist: pandas (==1.5.0)
Requires-Dist: psycopg2-binary (==2.9.3)
Requires-Dist: pycocotools (==2.0.4)
Requires-Dist: pykalman (>=0.9.5,<0.10.0)
Requires-Dist: python-dotenv (>=0.21.0,<0.22.0)
Requires-Dist: scikit-learn (>=1.1.0,<2.0.0)
Requires-Dist: scikit-video (>=1.1.11,<2.0.0)
Requires-Dist: scipy (==1.7.3)
Requires-Dist: torch (>=1.13.0,<2.0.0)
Requires-Dist: torchvision (>=0.14.0,<0.15.0)
Requires-Dist: tqdm (>=4.64.1,<5.0.0)
Requires-Dist: yolov5 (>=6.2.3,<7.0.0)
Project-URL: Repository, https://github.com/surfriderfoundationeurope/surfnet
